real_package/__init__.py
real_package-0.0.2.dist-info/LICENSE
real_package-0.0.2.dist-info/METADATA
real_package-0.0.2.dist-info/WHEEL
real_package-0.0.2.dist-info/top_level.txt
real_package-0.0.2.dist-info/RECORD
