Metadata-Version: 2.1
Name: real-package
Version: 0.0.2
Summary: A very real package
Author-email: Paul Francis Cunninghame Mathews <pfcmathews+pypi@gmail.com>
Classifier: Programming Language :: Python :: 3
Classifier: License :: OSI Approved :: MIT License
Classifier: Operating System :: OS Independent
Requires-Python: >=3.6
License-File: LICENSE
